autogenai/__init__.py
autogenai/cli.py
autogenai/tools.py
autogenai/core/__init__.py
autogenai/core/base.py
autogenai/core/factory.py
autogenai/core/gemini_engine.py
autogenai/core/openai_engine.py
autogenai/utils/__init__.py
autogenai/utils/config.py
autogenai/utils/errors.py
autogenai/utils/logger.py
autogenai-0.1.1.dist-info/licenses/LICENSE
autogenai-0.1.1.dist-info/METADATA
autogenai-0.1.1.dist-info/WHEEL
autogenai-0.1.1.dist-info/entry_points.txt
autogenai-0.1.1.dist-info/top_level.txt
autogenai-0.1.1.dist-info/RECORD
