Metadata-Version: 2.4
Name: autogenai
Version: 0.1.1
Summary: Early-stage unified SDK for OpenAI, Gemini and more
Author-email: Sanin K <dev.sanink@gmail.com>
License-Expression: MIT
Project-URL: Homepage, https://github.com/sanin7k/autogenai.git
Classifier: Development Status :: 3 - Alpha
Classifier: Intended Audience :: Developers
Classifier: Programming Language :: Python :: 3.8
Classifier: Programming Language :: Python :: 3.9
Classifier: Programming Language :: Python :: 3.10
Classifier: Topic :: Software Development :: Libraries
Requires-Python: >=3.8
License-File: LICENSE
Requires-Dist: httpx<1.0.0,>=0.26.0
Requires-Dist: python-dotenv<2.0.0,>=1.0.0
Requires-Dist: google-generativeai<1.0.0,>=0.3.2
Provides-Extra: openai
Requires-Dist: openai<2.0.0,>=1.0.0; extra == "openai"
Dynamic: license-file
